opfuncs/__init__.py
opfuncs/_opfunc.py
opfuncs-1.0.1.dist-info/LICENSE
opfuncs-1.0.1.dist-info/METADATA
opfuncs-1.0.1.dist-info/WHEEL
opfuncs-1.0.1.dist-info/top_level.txt
opfuncs-1.0.1.dist-info/RECORD
