Metadata-Version: 2.1
Name: opfuncs
Version: 1.0.1
Summary: A package to enable the usage of operators on python functions
Home-page: https://github.com/sqrtdan/opfuncs
Author: sqrtdan
Author-email: sqrtdan@gmail.com
License: MIT
Classifier: License :: OSI Approved :: MIT License
Classifier: Programming Language :: Python :: 3
Classifier: Programming Language :: Python :: 3 :: Only
Requires-Python: >=3.10
License-File: LICENSE
